codalab_service.py
codalab/__init__.py
codalab/common.py
codalab/bin/__init__.py
codalab/bin/bundle_manager.py
codalab/bin/cl.py
codalab/bin/server.py
codalab/bin/ws_server.py
codalab/bundles/__init__.py
codalab/bundles/dataset_bundle.py
codalab/bundles/derived_bundle.py
codalab/bundles/make_bundle.py
codalab/bundles/named_bundle.py
codalab/bundles/private_bundle.py
codalab/bundles/program_bundle.py
codalab/bundles/run_bundle.py
codalab/bundles/uploaded_bundle.py
codalab/client/__init__.py
codalab/client/json_api_client.py
codalab/lib/__init__.py
codalab/lib/bundle_action.py
codalab/lib/bundle_cli.py
codalab/lib/bundle_fuse.py
codalab/lib/bundle_store.py
codalab/lib/bundle_util.py
codalab/lib/canonicalize.py
codalab/lib/cli_util.py
codalab/lib/codalab_manager.py
codalab/lib/completers.py
codalab/lib/crypt_util.py
codalab/lib/download_manager.py
codalab/lib/editor_util.py
codalab/lib/emailer.py
codalab/lib/file_util.py
codalab/lib/formatting.py
codalab/lib/interactive_session.py
codalab/lib/metadata_defaults.py
codalab/lib/metadata_util.py
codalab/lib/path_util.py
codalab/lib/print_util.py
codalab/lib/profiling_util.py
codalab/lib/server_util.py
codalab/lib/spec_util.py
codalab/lib/telemetry_util.py
codalab/lib/ui_actions.py
codalab/lib/unicode_util.py
codalab/lib/upload_manager.py
codalab/lib/worksheet_util.py
codalab/lib/zip_util.py
codalab/lib/beam/MultiReaderFileStream.py
codalab/lib/beam/SQLiteIndexedTar.py
codalab/lib/beam/__init__.py
codalab/lib/beam/blobstorageuploader.py
codalab/lib/beam/filesystems.py
codalab/lib/beam/mockblobstoragefilesystem.py
codalab/lib/beam/streamingzipfile.py
codalab/model/__init__.py
codalab/model/bundle_model.py
codalab/model/mysql_model.py
codalab/model/orm_object.py
codalab/model/sqlite_model.py
codalab/model/tables.py
codalab/model/util.py
codalab/model/worker_model.py
codalab/objects/__init__.py
codalab/objects/bundle.py
codalab/objects/dependency.py
codalab/objects/metadata.py
codalab/objects/metadata_spec.py
codalab-1.7.5.dist-info/LICENSE.txt
codalab-1.7.5.dist-info/METADATA
codalab-1.7.5.dist-info/WHEEL
codalab-1.7.5.dist-info/entry_points.txt
codalab-1.7.5.dist-info/top_level.txt
codalab-1.7.5.dist-info/RECORD
