Metadata-Version: 2.1
Name: codalab
Version: 1.7.5
Summary: CLI for CodaLab, a platform for reproducible computation
Home-page: https://github.com/codalab/codalab-worksheets
Author: CodaLab
Author-email: codalab.worksheets@gmail.com
License: Apache License 2.0
Keywords: codalab reproducible computation worksheets competitions
Platform: UNKNOWN
Classifier: Programming Language :: Python :: 3 :: Only
Classifier: Programming Language :: Python :: 3.9
Classifier: License :: OSI Approved :: Apache Software License
Requires-Python: ~=3.9
License-File: LICENSE.txt
Requires-Dist: wheel ==0.43.0
Requires-Dist: apache-beam[azure] ==2.38.0
Requires-Dist: cachetools <5,>=3.1.0
Requires-Dist: google-apitools <0.5.32,>=0.5.31
Requires-Dist: google-auth <3,>=1.18.0
Requires-Dist: bottle ==0.12.20
Requires-Dist: docker ==4.3.0
Requires-Dist: marshmallow-jsonapi ==0.15.1
Requires-Dist: marshmallow ==2.15.1
Requires-Dist: setuptools >=40.0.0
Requires-Dist: argcomplete ==1.12.3
Requires-Dist: indexed-gzip ==1.7.0
Requires-Dist: ratarmountcore ==0.1.3
Requires-Dist: PyYAML ==6.0.1
Requires-Dist: psutil ==5.7.2
Requires-Dist: six ==1.15.0
Requires-Dist: SQLAlchemy ==1.3.19
Requires-Dist: watchdog >=2.0.0
Requires-Dist: fusepy ==2.0.4
Requires-Dist: pygments <2.13,>=2.12
Requires-Dist: click ==8.0.2
Requires-Dist: python-dateutil ==2.8.1
Requires-Dist: diffimg ==0.2.3
Requires-Dist: selenium ==3.141.0
Requires-Dist: requests ==2.25.0
Requires-Dist: azure-storage-blob ==12.4.0
Requires-Dist: azure-core ==1.8.0
Requires-Dist: sentry-sdk ==1.14.0
Requires-Dist: requests-oauthlib ==1.1.0
Requires-Dist: oauthlib ==2.1.0
Requires-Dist: markdown2 ==2.4.0
Requires-Dist: urllib3 ==1.26.11
Requires-Dist: retry ==0.9.2
Requires-Dist: spython ==0.1.14
Requires-Dist: flufl.lock ==6.0
Requires-Dist: websockets ==9.1
Requires-Dist: kubernetes ==12.0.1
Requires-Dist: google-cloud-storage ==2.0.0
Requires-Dist: httpio ==0.3.0
Requires-Dist: memory-profiler ==0.61.0
